applications/tkcontrollerapp.py
nipiezojenapy/__init__.py
nipiezojenapy/controller.py
nipiezojenapy-1.0.4.dist-info/LICENSE.txt
nipiezojenapy-1.0.4.dist-info/METADATA
nipiezojenapy-1.0.4.dist-info/WHEEL
nipiezojenapy-1.0.4.dist-info/entry_points.txt
nipiezojenapy-1.0.4.dist-info/top_level.txt
nipiezojenapy-1.0.4.dist-info/RECORD
