Metadata-Version: 2.1
Name: nipiezojenapy
Version: 1.0.4
Summary: A package for controlling Jena PiezoSystem NV40 3CLE amplifier vi NIDAQMX.
Author-email: "G. Adam Cox" <gadamc@gmail.com>
Maintainer-email: "G. Adam Cox" <gadamc@gmail.com>, Maxwell Parsons <mfpars@uw.edu>
Project-URL: Homepage, https://github.com/qt3uw/nipiezojenapy
Project-URL: Source, https://github.com/qt3uw/nipiezojenapy
Project-URL: Bug Tracker, https://github.com/qt3uw/nipiezojenapy/issues
Project-URL: Changelog, https://github.com/qt3uw/nipiezojenapy/releases
Keywords: qt3,National Instruments,Jena,piezo,stage,control
Classifier: Development Status :: 5 - Production/Stable
Classifier: Intended Audience :: Science/Research
Classifier: Topic :: Scientific/Engineering :: Physics
Classifier: Topic :: Scientific/Engineering
Classifier: License :: OSI Approved :: BSD License
Classifier: Programming Language :: Python :: 3.8
Classifier: Programming Language :: Python :: 3.9
Classifier: Programming Language :: Python :: 3.10
Classifier: Programming Language :: Python :: 3.11
Classifier: Programming Language :: Python :: 3 :: Only
Requires-Python: >=3.8
License-File: LICENSE.txt
Requires-Dist: nidaqmx >=0.6.3
Requires-Dist: numpy >=1.21.2
